{
  "services": [
    {
      "title": "Internet lenta",
      "description": "Internet lenta em todo setor de compras",
      "category": "Acesso",
      "status": "Finalizado",
      "createDate": "2026-03-29 11:27:42",
      "id": "GKJP5qWzItk"
    },
    {
      "title": "Pacote office",
      "description": "Intalação de pacote office na máquina id: 777",
      "category": "Software",
      "status": "Aberto",
      "createDate": "2026-03-29 11:29:51",
      "id": "MggJkCX-igM"
    },
    {
      "title": "Criar novo acesso",
      "description": "Criar acesso para o usuário joao@souza",
      "category": "Acesso",
      "status": "Cancelado",
      "createDate": "2026-03-29 11:40:28",
      "id": "Rr8siu_Gb3M"
    },
    {
      "title": "Novo acesso",
      "description": "Criar novo acesso para o usuário pedro@lima",
      "category": "Acesso",
      "status": "Em atendimento",
      "createDate": "2026-03-29 11:42:43",
      "id": "tRTnraf7wXI"
    },
    {
      "title": "Falha na conexão",
      "description": "Não estou conseguindo conextar à internet",
      "category": "Conexão",
      "status": "Aberto",
      "createDate": "2026-03-29 14:00:48",
      "id": "IdGZmc-zcQI"
    },
    {
      "title": "Novo mouse",
      "description": "Preciso de um novo mouse para a máquina id 78899",
      "category": "Infra",
      "status": "Finalizado",
      "createDate": "2026-03-29 14:01:30",
      "id": "bLUi0HKm9yg"
    }
  ],
  "$schema": "./node_modules/json-server/schema.json"
}